setup.cfg
setup.py
lava_logger/Logger.py
lava_logger/__init__.py
lava_logger.egg-info/PKG-INFO
lava_logger.egg-info/SOURCES.txt
lava_logger.egg-info/dependency_links.txt
lava_logger.egg-info/not-zip-safe
lava_logger.egg-info/top_level.txt