Metadata-Version: 1.0
Name: lava-logger
Version: 1.0.1
Summary: Custom logger by lava_frai
Home-page: UNKNOWN
Author: UNKNOWN
Author-email: lavafrai@yandex.ru
License: UNKNOWN
Platform: UNKNOWN
